JiaoniChaogupiaoZhichanlunXinjie/README.md
JiaoniChaogupiaoZhichanlunXinjie/__init__.py
JiaoniChaogupiaoZhichanlunXinjie/__main__.py
JiaoniChaogupiaoZhichanlunXinjie/file.epub
JiaoniChaogupiaoZhichanlunXinjie/index.html
JiaoniChaogupiaoZhichanlunXinjie/css/__init__.py
JiaoniChaogupiaoZhichanlunXinjie/css/annotations.css
JiaoniChaogupiaoZhichanlunXinjie/css/main.css
JiaoniChaogupiaoZhichanlunXinjie/css/normalize.css
JiaoniChaogupiaoZhichanlunXinjie/css/popup.css
JiaoniChaogupiaoZhichanlunXinjie/font/__init__.py
JiaoniChaogupiaoZhichanlunXinjie/font/fontello.eot
JiaoniChaogupiaoZhichanlunXinjie/font/fontello.svg
JiaoniChaogupiaoZhichanlunXinjie/font/fontello.ttf
JiaoniChaogupiaoZhichanlunXinjie/font/fontello.woff
JiaoniChaogupiaoZhichanlunXinjie/img/__init__.py
JiaoniChaogupiaoZhichanlunXinjie/img/annotator-glyph-sprite.png
JiaoniChaogupiaoZhichanlunXinjie/img/annotator-icon-sprite.png
JiaoniChaogupiaoZhichanlunXinjie/img/apple-touch-icon.png
JiaoniChaogupiaoZhichanlunXinjie/img/cancelfullscreen.png
JiaoniChaogupiaoZhichanlunXinjie/img/close.png
JiaoniChaogupiaoZhichanlunXinjie/img/fullscreen.png
JiaoniChaogupiaoZhichanlunXinjie/img/loader.gif
JiaoniChaogupiaoZhichanlunXinjie/img/menu-icon.png
JiaoniChaogupiaoZhichanlunXinjie/img/save.png
JiaoniChaogupiaoZhichanlunXinjie/img/saved.png
JiaoniChaogupiaoZhichanlunXinjie/img/settings-s.png
JiaoniChaogupiaoZhichanlunXinjie/img/settings.png
JiaoniChaogupiaoZhichanlunXinjie/img/star.png
JiaoniChaogupiaoZhichanlunXinjie/js/__init__.py
JiaoniChaogupiaoZhichanlunXinjie/js/epub.js
JiaoniChaogupiaoZhichanlunXinjie/js/epub.min.js
JiaoniChaogupiaoZhichanlunXinjie/js/epub.min.map
JiaoniChaogupiaoZhichanlunXinjie/js/hooks.min.js
JiaoniChaogupiaoZhichanlunXinjie/js/hooks.min.map
JiaoniChaogupiaoZhichanlunXinjie/js/reader.js
JiaoniChaogupiaoZhichanlunXinjie/js/reader.js.map
JiaoniChaogupiaoZhichanlunXinjie/js/reader.min.js
JiaoniChaogupiaoZhichanlunXinjie/js/reader.min.map
JiaoniChaogupiaoZhichanlunXinjie/js/hooks/__init__.py
jiaoni_chaogupiao_zhichanlun_xinjie-2022.10.15.0.dist-info/METADATA
jiaoni_chaogupiao_zhichanlun_xinjie-2022.10.15.0.dist-info/WHEEL
jiaoni_chaogupiao_zhichanlun_xinjie-2022.10.15.0.dist-info/entry_points.txt
jiaoni_chaogupiao_zhichanlun_xinjie-2022.10.15.0.dist-info/top_level.txt
jiaoni_chaogupiao_zhichanlun_xinjie-2022.10.15.0.dist-info/RECORD
